{
  "suggestions": [
    {
      "name": "firstname.blockchain",
      "price": 0
    },
    {
      "name": "firstname.blockchain",
      "price": 0
    },
    {
      "name": "firstname264.blockchain",
      "price": 0
    },
    {
      "name": "latefirstname6.blockchain",
      "price": 0
    },
    {
      "name": "firstnamecat479.blockchain",
      "price": 0
    },
    {
      "name": "firstnamerat697.blockchain",
      "price": 0
    },
    {
      "name": "wildfirstname99.blockchain",
      "price": 0
    },
    {
      "name": "firstnamedane31.blockchain",
      "price": 0
    },
    {
      "name": "firstnamepig240.blockchain",
      "price": 0
    },
    {
      "name": "crudefirstname67.blockchain",
      "price": 0
    },
    {
      "name": "rarefirstname884.blockchain",
      "price": 0
    },
    {
      "name": "warmfirstname487.blockchain",
      "price": 0
    },
    {
      "name": "glibfirstname448.blockchain",
      "price": 0
    },
    {
      "name": "weakfirstname416.blockchain",
      "price": 0
    },
    {
      "name": "firstnameotter20.blockchain",
      "price": 0
    },
    {
      "name": "sickfirstname463.blockchain",
      "price": 0
    },
    {
      "name": "firstnamegoat468.blockchain",
      "price": 0
    },
    {
      "name": "cozyfirstname630.blockchain",
      "price": 0
    },
    {
      "name": "greyfirstname441.blockchain",
      "price": 0
    },
    {
      "name": "firstnamelamb722.blockchain",
      "price": 0
    },
    {
      "name": "firstnameapso483.blockchain",
      "price": 0
    },
    {
      "name": "teenyfirstname385.blockchain",
      "price": 0
    },
    {
      "name": "soberfirstname669.blockchain",
      "price": 0
    },
    {
      "name": "naivefirstname391.blockchain",
      "price": 0
    },
    {
      "name": "bumpyfirstname433.blockchain",
      "price": 0
    },
    {
      "name": "decentfirstname74.blockchain",
      "price": 0
    },
    {
      "name": "firstnamepanda596.blockchain",
      "price": 0
    },
    {
      "name": "blackfirstname801.blockchain",
      "price": 0
    },
    {
      "name": "firstnamestork410.blockchain",
      "price": 0
    },
    {
      "name": "curvyfirstname211.blockchain",
      "price": 0
    }
  ]
}
